motif_jupyter/__init__.py
motif_jupyter/_frontend.py
motif_jupyter/_version.py
motif_jupyter/example.py
motif_jupyter/motif.py
motif_jupyter/labextension/package.json
motif_jupyter/labextension/static/30.35a65430f70723dbaa12.js
motif_jupyter/labextension/static/355.22c6c42152c9d7f83c29.js
motif_jupyter/labextension/static/419.68b76a98afd682808fc3.js
motif_jupyter/labextension/static/480.52559c27616adb9d6fc6.js
motif_jupyter/labextension/static/565.b80b584f4d94261839c2.js
motif_jupyter/labextension/static/565.b80b584f4d94261839c2.js.LICENSE.txt
motif_jupyter/labextension/static/568.386deaf3881ca05ccd2a.js
motif_jupyter/labextension/static/597.464ab72911e8926099a0.js
motif_jupyter/labextension/static/70.1f95733babb61b395612.js
motif_jupyter/labextension/static/811.5604b363d2aae26c33cf.js
motif_jupyter/labextension/static/811.5604b363d2aae26c33cf.js.LICENSE.txt
motif_jupyter/labextension/static/886.6de08759240eb625bda0.js
motif_jupyter/labextension/static/940.31d1af331f0c619f4a40.js
motif_jupyter/labextension/static/940.31d1af331f0c619f4a40.js.LICENSE.txt
motif_jupyter/labextension/static/remoteEntry.d9ee177591089fb1c04e.js
motif_jupyter/labextension/static/style.js
motif_jupyter/nbextension/extension.js
motif_jupyter/nbextension/index.js
motif_jupyter/nbextension/index.js.LICENSE.txt
motif_jupyter/nbextension/index.js.map
motif_jupyter/tests/__init__.py
motif_jupyter/tests/conftest.py
motif_jupyter/tests/test_example.py
motif_jupyter/tests/test_nbextension_path.py
motif_jupyter-0.0.1b5.data/data/etc/jupyter/nbconfig/notebook.d/motif_jupyter.json
motif_jupyter-0.0.1b5.data/data/share/jupyter/labextensions/motif-jupyter/package.json
motif_jupyter-0.0.1b5.data/data/share/jupyter/labextensions/motif-jupyter/static/30.35a65430f70723dbaa12.js
motif_jupyter-0.0.1b5.data/data/share/jupyter/labextensions/motif-jupyter/static/355.22c6c42152c9d7f83c29.js
motif_jupyter-0.0.1b5.data/data/share/jupyter/labextensions/motif-jupyter/static/419.68b76a98afd682808fc3.js
motif_jupyter-0.0.1b5.dist-info/LICENSE.txt
motif_jupyter-0.0.1b5.dist-info/METADATA
motif_jupyter-0.0.1b5.dist-info/WHEEL
motif_jupyter-0.0.1b5.dist-info/top_level.txt
motif_jupyter-0.0.1b5.dist-info/RECORD
